[
  {
    "name": ".45 ACP AP",
    "price": 1680,
    "level": 4,
    "type": ".45"
  },
  {
    "name": ".45 ACP FMJ",
    "price": 536,
    "level": 3,
    "type": ".45"
  },
  {
    "name": ".45 ACP RIP",
    "price": 515,
    "level": 3,
    "type": ".45"
  },
  {
    "name": "12.7x55mm PS12A",
    "price": 589,
    "level": 3,
    "type": "12.7x55mm"
  },
  {
    "name": "12.7x55mm PS12B",
    "price": 5143,
    "level": 5,
    "type": "12.7x55mm"
  },
  {
    "name": "12.7x55mm PD12双头弹",
    "price": 3367,
    "level": 4,
    "type": "12.7x55mm"
  },
  {
    "name": "5.45x39mm BS",
    "price": 4639,
    "level": 5,
    "type": "5.45x39mm"
  },
  {
    "name": "5.45x39mm BT",
    "price": 1316,
    "level": 4,
    "type": "5.45x39mm"
  },
  {
    "name": "5.45x39mm PS",
    "price": 504,
    "level": 3,
    "type": "5.45x39mm"
  },
  {
    "name": "5.56x45mm M995",
    "price": 3107,
    "level": 5,
    "type": "5.56x45mm"
  },
  {
    "name": "5.56x45mm M855A1",
    "price": 1701,
    "level": 4,
    "type": "5.56x45mm"
  },
  {
    "name": "5.7x28mm R37.F",
    "price": 387,
    "level": 3,
    "type": "5.7x28mm"
  },
  {
    "name": "5.7x28mm SS190",
    "price": 4247,
    "level": 5,
    "type": "5.7x28mm"
  },
  {
    "name": "5.7x28mm SS193",
    "price": 1653,
    "level": 4,
    "type": "5.7x28mm"
  },
  {
    "name": "5.7x28mm L191",
    "price": 495,
    "level": 3,
    "type": "5.7x28mm"
  },
  {
    "name": "5.8x42mm DBP10",
    "price": 1953,
    "level": 4,
    "type": "5.8x42mm"
  },
  {
    "name": "5.8x42mm DVP88",
    "price": 298,
    "level": 3,
    "type": "5.8x42mm"
  },
  {
    "name": "5.8x42mm DVC12",
    "price": 4445,
    "level": 5,
    "type": "5.8x42mm"
  },
  {
    "name": "6.8x51mm FMJ",
    "price": 2114,
    "level": 4,
    "type": "6.8x51mm"
  },
  {
    "name": "6.8x51mm Hybrid",
    "price": 4029,
    "level": 5,
    "type": "6.8x51mm"
  },
  {
    "name": "7.62x39mm PS",
    "price": 506,
    "level": 3,
    "type": "7.62x39mm"
  },
  {
    "name": "7.62x39mm AP",
    "price": 2796,
    "level": 5,
    "type": "7.62x39mm"
  },
  {
    "name": "7.62x39mm BP",
    "price": 1506,
    "level": 4,
    "type": "7.62x39mm"
  },
  {
    "name": "7.62x51mm M80",
    "price": 1938,
    "level": 4,
    "type": "7.62x51mm"
  },
  {
    "name": "7.62x51mm BPZ",
    "price": 608,
    "level": 3,
    "type": "7.62x51mm"
  },
  {
    "name": "7.62x51mm M62",
    "price": 4667,
    "level": 5,
    "type": "7.62x51mm"
  },
  {
    "name": "7.62x54R BT",
    "price": 3214,
    "level": 5,
    "type": "7.62x54R"
  },
  {
    "name": "7.62x54R LPS",
    "price": 1850,
    "level": 4,
    "type": "7.62x54R"
  },
  {
    "name": "7.62x54R T46M",
    "price": 582,
    "level": 3,
    "type": "7.62x54R"
  },
  {
    "name": "9x19mm PBP",
    "price": 1546,
    "level": 4,
    "type": "9x19mm"
  },
  {
    "name": "9x19mm AP6.3",
    "price": 381,
    "level": 3,
    "type": "9x19mm"
  },
  {
    "name": "9x19mm RIP",
    "price": 458,
    "level": 3,
    "type": "9x19mm"
  },
  {
    "name": "9x39mm SP5",
    "price": 644,
    "level": 3,
    "type": "9x39mm"
  },
  {
    "name": "9x39mm BP",
    "price": 4809,
    "level": 5,
    "type": "9x39mm"
  },
  {
    "name": "9x39mm SP6",
    "price": 1961,
    "level": 4,
    "type": "9x39mm"
  },
  {
    "name": "4.6x30mm AP SX",
    "price": 3997,
    "level": 5,
    "type": "4.6x30mm"
  },
  {
    "name": "4.6x30mm FMJ SX",
    "price": 1620,
    "level": 4,
    "type": "4.6x30mm"
  },
  {
    "name": "4.6x30mm Subsonic SX",
    "price": 477,
    "level": 3,
    "type": "4.6x30mm"
  },
  {
    "name": "5.56x45mm M855",
    "price": 481,
    "level": 3,
    "type": "5.56x45mm"
  },
  {
    "name": "12.7x55mm PS12",
    "price": 2622,
    "level": 4,
    "type": "12.7x55mm"
  }
]